rova/__init__.py
rova/rova.py
rova-0.3.0.dist-info/LICENSE
rova-0.3.0.dist-info/METADATA
rova-0.3.0.dist-info/WHEEL
rova-0.3.0.dist-info/top_level.txt
rova-0.3.0.dist-info/RECORD
