Metadata-Version: 2.1
Name: rova
Version: 0.3.0
Summary: API wrapper for ROVA calendar
Home-page: https://github.com/GidoHakvoort/rova
Author: Gido Hakvoort
Author-email: gido@hakvoort.it
License: UNKNOWN
Platform: UNKNOWN
Classifier: Programming Language :: Python :: 3
Classifier: License :: OSI Approved :: MIT License
Classifier: Operating System :: OS Independent
